Metadata-Version: 2.4
Name: pubmed-citation-update
Version: 0.1.5
Summary: A tool for collecting citation data from PubMed and analyzing author relationships
Home-page: https://github.com/yourusername/pubmed-citation
Author: Armelle,Brandon,Shanta
Author-email: your.email@example.com
Project-URL: Bug Tracker, https://github.com/yourusername/pubmed-citation/issues
Classifier: Programming Language :: Python :: 3
Classifier: Programming Language :: Python :: 3.6
Classifier: Programming Language :: Python :: 3.7
Classifier: Programming Language :: Python :: 3.8
Classifier: Programming Language :: Python :: 3.9
Classifier: License :: OSI Approved :: MIT License
Classifier: Operating System :: OS Independent
Classifier: Topic :: Scientific/Engineering :: Bio-Informatics
Classifier: Topic :: Scientific/Engineering :: Information Analysis
Requires-Python: >=3.6
Requires-Dist: requests>=2.25.0
Requires-Dist: numpy>=1.19.0
Requires-Dist: scipy>=1.5.0
Provides-Extra: viz
Requires-Dist: networkx>=2.5; extra == "viz"
Requires-Dist: matplotlib>=3.3.0; extra == "viz"
Dynamic: author
Dynamic: author-email
Dynamic: classifier
Dynamic: description
Dynamic: description-content-type
Dynamic: home-page
Dynamic: project-url
Dynamic: provides-extra
Dynamic: requires-dist
Dynamic: requires-python
Dynamic: summary
